{"openapi":"3.1.0","info":{"title":"MiniSocial API","description":"Sample API of MiniSocial endpoints and architecture","contact":{"name":"David Martín","url":"https://github.com/davidmart7n","email":"davidmartinencuentra@gmail.com"},"license":{"name":"Apache 2.0","url":"http://springdoc.org"},"version":"1.0.0"},"externalDocs":{"description":"GitHub repository of the project","url":"https://github.com/davidmart7n/MiniSocial"},"servers":[{"url":"http://localhost:9090","description":"Generated server url"}],"paths":{"/videos/update/{id}":{"put":{"tags":["video-controller"],"operationId":"update","parameters":[{"name":"id","in":"path","required":true,"schema":{"type":"integer","format":"int64"}}],"requestBody":{"content":{"application/json":{"schema":{"$ref":"#/components/schemas/VideoRequestDTO"}}},"required":true},"responses":{"200":{"description":"OK","content":{"*/*":{"schema":{"$ref":"#/components/schemas/VideoResponseDTO"}}}}}}},"/users/update/{id}":{"put":{"tags":["user-controller"],"operationId":"update_1","parameters":[{"name":"id","in":"path","required":true,"schema":{"type":"integer","format":"int64"}}],"requestBody":{"content":{"application/json":{"schema":{"$ref":"#/components/schemas/UserRequestDTO"}}},"required":true},"responses":{"200":{"description":"OK","content":{"*/*":{"schema":{"$ref":"#/components/schemas/UserResponseDTO"}}}}}}},"/creators/{id}":{"get":{"tags":["creator-controller"],"operationId":"get","parameters":[{"name":"id","in":"path","required":true,"schema":{"type":"integer","format":"int64"}}],"responses":{"200":{"description":"OK","content":{"*/*":{"schema":{"$ref":"#/components/schemas/CreatorResponseDTO"}}}}}},"put":{"tags":["creator-controller"],"operationId":"update_2","parameters":[{"name":"id","in":"path","required":true,"schema":{"type":"integer","format":"int64"}}],"requestBody":{"content":{"application/json":{"schema":{"$ref":"#/components/schemas/CreatorRequestDTO"}}},"required":true},"responses":{"200":{"description":"OK","content":{"*/*":{"schema":{"$ref":"#/components/schemas/CreatorResponseDTO"}}}}}},"delete":{"tags":["creator-controller"],"operationId":"delete","parameters":[{"name":"id","in":"path","required":true,"schema":{"type":"integer","format":"int64"}}],"responses":{"200":{"description":"OK"}}}},"/videos/{videoId}/like/{userId}":{"post":{"tags":["video-controller"],"operationId":"likeVideo","parameters":[{"name":"videoId","in":"path","required":true,"schema":{"type":"integer","format":"int64"}},{"name":"userId","in":"path","required":true,"schema":{"type":"integer","format":"int64"}}],"responses":{"200":{"description":"OK"}}}},"/videos/create":{"post":{"tags":["video-controller"],"operationId":"create","requestBody":{"content":{"application/json":{"schema":{"$ref":"#/components/schemas/VideoRequestDTO"}}},"required":true},"responses":{"200":{"description":"OK","content":{"*/*":{"schema":{"$ref":"#/components/schemas/VideoResponseDTO"}}}}}}},"/users/{userId}/follow/{creatorId}":{"post":{"tags":["user-controller"],"operationId":"follow","parameters":[{"name":"userId","in":"path","required":true,"schema":{"type":"integer","format":"int64"}},{"name":"creatorId","in":"path","required":true,"schema":{"type":"integer","format":"int64"}}],"responses":{"200":{"description":"OK"}}}},"/users/create":{"post":{"tags":["user-controller"],"operationId":"create_1","requestBody":{"content":{"application/json":{"schema":{"$ref":"#/components/schemas/UserRequestDTO"}}},"required":true},"responses":{"200":{"description":"OK","content":{"*/*":{"schema":{"$ref":"#/components/schemas/UserResponseDTO"}}}}}}},"/creators/create":{"post":{"tags":["creator-controller"],"operationId":"create_2","requestBody":{"content":{"application/json":{"schema":{"$ref":"#/components/schemas/CreatorRequestDTO"}}},"required":true},"responses":{"200":{"description":"OK","content":{"*/*":{"schema":{"$ref":"#/components/schemas/CreatorResponseDTO"}}}}}}},"/videos/{id}":{"get":{"tags":["video-controller"],"operationId":"get_1","parameters":[{"name":"id","in":"path","required":true,"schema":{"type":"integer","format":"int64"}}],"responses":{"200":{"description":"OK","content":{"*/*":{"schema":{"$ref":"#/components/schemas/VideoResponseDTO"}}}}}}},"/videos/creator/{creatorId}":{"get":{"tags":["video-controller"],"operationId":"getVideosByCreator","parameters":[{"name":"creatorId","in":"path","required":true,"schema":{"type":"integer","format":"int64"}}],"responses":{"200":{"description":"OK","content":{"*/*":{"schema":{"type":"array","items":{"$ref":"#/components/schemas/VideoResponseDTO"}}}}}}}},"/videos/all":{"get":{"tags":["video-controller"],"operationId":"getAllVideos","responses":{"200":{"description":"OK","content":{"*/*":{"schema":{"type":"array","items":{"$ref":"#/components/schemas/VideoResponseDTO"}}}}}}}},"/users/{id}":{"get":{"tags":["user-controller"],"operationId":"get_2","parameters":[{"name":"id","in":"path","required":true,"schema":{"type":"integer","format":"int64"}}],"responses":{"200":{"description":"OK","content":{"*/*":{"schema":{"$ref":"#/components/schemas/UserResponseDTO"}}}}}}},"/users/all":{"get":{"tags":["user-controller"],"operationId":"getAllUsers","responses":{"200":{"description":"OK","content":{"*/*":{"schema":{"type":"array","items":{"$ref":"#/components/schemas/UserResponseDTO"}}}}}}}},"/creators/all":{"get":{"tags":["creator-controller"],"operationId":"getAllCreators","responses":{"200":{"description":"OK","content":{"*/*":{"schema":{"type":"array","items":{"$ref":"#/components/schemas/CreatorResponseDTO"}}}}}}}},"/videos/delete/{id}":{"delete":{"tags":["video-controller"],"operationId":"delete_1","parameters":[{"name":"id","in":"path","required":true,"schema":{"type":"integer","format":"int64"}}],"responses":{"200":{"description":"OK"}}}},"/users/{userId}/unfollow/{creatorId}":{"delete":{"tags":["user-controller"],"operationId":"unfollow","parameters":[{"name":"userId","in":"path","required":true,"schema":{"type":"integer","format":"int64"}},{"name":"creatorId","in":"path","required":true,"schema":{"type":"integer","format":"int64"}}],"responses":{"200":{"description":"OK"}}}},"/users/delete/{id}":{"delete":{"tags":["user-controller"],"operationId":"delete_2","parameters":[{"name":"id","in":"path","required":true,"schema":{"type":"integer","format":"int64"}}],"responses":{"200":{"description":"OK"}}}}},"components":{"schemas":{"VideoRequestDTO":{"type":"object","properties":{"creatorId":{"type":"integer","format":"int64"},"title":{"type":"string"},"description":{"type":"string"}}},"VideoResponseDTO":{"type":"object","properties":{"id":{"type":"integer","format":"int64"},"creatorId":{"type":"integer","format":"int64"},"title":{"type":"string"},"description":{"type":"string"},"likes":{"type":"integer","format":"int32"}}},"UserRequestDTO":{"type":"object","properties":{"username":{"type":"string","maxLength":2147483647,"minLength":4},"email":{"type":"string","format":"email","minLength":1},"bio":{"type":"string"}},"required":["email","username"]},"UserResponseDTO":{"type":"object","properties":{"id":{"type":"integer","format":"int64"},"username":{"type":"string"},"email":{"type":"string"},"bio":{"type":"string"},"followingCreatorIds":{"type":"array","items":{"type":"integer","format":"int64"}}}},"CreatorRequestDTO":{"type":"object","properties":{"name":{"type":"string","maxLength":2147483647,"minLength":4},"email":{"type":"string","format":"email","minLength":1},"bio":{"type":"string"}},"required":["email","name"]},"CreatorResponseDTO":{"type":"object","properties":{"id":{"type":"integer","format":"int64"},"name":{"type":"string"},"email":{"type":"string"},"bio":{"type":"string"}}}}}}